[
    {
        "3": "AA"
    },
    {
        "4": "BC"
    },
    {
        "5": "DD"
    },
    {
        "6": "BC"
    },
    {
        "7": "CC"
    },
    {
        "9": "CD"
    },
    {
        "10": "BC"
    },
    {
        "11": "BC"
    },
    {
        "12": "BC"
    },
    {
        "13": "BC"
    },
    {
        "14": "CC"
    },
    {
        "15": "CD"
    },
    {
        "16": "CC"
    },
    {
        "17": "BC"
    },
    {
        "19": "CD"
    },
    {
        "20": "CD"
    },
    {
        "22": "CD"
    },
    {
        "24": "BB"
    },
    {
        "26": "CD"
    },
    {
        "27": "BB"
    },
    {
        "28": "BB"
    },
    {
        "29": "CC"
    },
    {
        "30": "BB"
    },
    {
        "31": "CC"
    },
    {
        "32": "BB"
    },
    {
        "33": "AA"
    },
    {
        "35": "CC"
    },
    {
        "36": "BC"
    },
    {
        "38": "BB"
    },
    {
        "39": "BC"
    },
    {
        "40": "BB"
    },
    {
        "41": "AB"
    },
    {
        "43": "CC"
    },
    {
        "44": "BB"
    },
    {
        "45": "AA"
    },
    {
        "46": "BB"
    },
    {
        "47": "BC"
    },
    {
        "48": "AB"
    },
    {
        "49": "AB"
    },
    {
        "50": "AA"
    },
    {
        "51": "AB"
    },
    {
        "52": "AB"
    },
    {
        "53": "BC"
    },
    {
        "54": "BC"
    },
    {
        "55": "BB"
    },
    {
        "56": "AA"
    },
    {
        "59": "AA"
    },
    {
        "60": "AB"
    },
    {
        "61": "BC"
    },
    {
        "62": "AA"
    },
    {
        "63": "BB"
    },
    {
        "64": "BC"
    },
    {
        "65": "BC"
    },
    {
        "66": "CC"
    },
    {
        "68": "BB"
    },
    {
        "72": "AB"
    },
    {
        "75": "BB"
    },
    {
        "76": "BB"
    },
    {
        "77": "BC"
    },
    {
        "78": "BC"
    },
    {
        "79": "BB"
    },
    {
        "1": "BC"
    },
    {
        "2": "CC"
    },
    {
        "8": "BB"
    },
    {
        "18": "BC"
    },
    {
        "21": "BB"
    },
    {
        "23": "AB"
    },
    {
        "25": "AB"
    },
    {
        "34": "BB"
    },
    {
        "37": "BB"
    },
    {
        "42": "BB"
    },
    {
        "57": "BB"
    },
    {
        "58": "BB"
    },
    {
        "67": "AA"
    },
    {
        "69": "AB"
    },
    {
        "70": "BC"
    },
    {
        "71": "BB"
    },
    {
        "73": "BC"
    },
    {
        "74": "AB"
    }
]